pgss/__init__.py
pgss/page_session_state.py
pgss-0.2.3.dist-info/LICENSE
pgss-0.2.3.dist-info/METADATA
pgss-0.2.3.dist-info/WHEEL
pgss-0.2.3.dist-info/top_level.txt
pgss-0.2.3.dist-info/RECORD
