Metadata-Version: 2.1
Name: pgss
Version: 0.2.3
Summary: A package to manage session states per page in Streamlit
Home-page: https://github.com/masashi2ueda/pgss
Author: Masashi Ueda
Author-email: 
Classifier: Development Status :: 3 - Alpha
Classifier: Intended Audience :: Developers
Classifier: License :: OSI Approved :: MIT License
Classifier: Programming Language :: Python :: 3
Classifier: Programming Language :: Python :: 3.7
Classifier: Programming Language :: Python :: 3.8
Classifier: Programming Language :: Python :: 3.9
Classifier: Programming Language :: Python :: 3.10
Requires-Python: >=3.7
License-File: LICENSE
Requires-Dist: streamlit>=1.0
